{"packets":[{"SeqNum":1,"Channel":"SnapshotB","Messages":[{"SecurityID":1,"RepSeqNum":22,"LastMsgSeqNumProcessed":20,"MultiBook":{"Buys":[{"Side":"BUY","Quantity":1,"Price":19932,"NumOrders":1},{"Side":"BUY","Quantity":1,"Price":11052,"NumOrders":1},{"Side":"BUY","Quantity":1,"Price":9728,"NumOrders":1},{"Side":"BUY","Quantity":1,"Price":2,"NumOrders":1},{"Side":"BUY","Quantity":1,"Price":1,"NumOrders":1}],"Sells":[{"Side":"SELL","Quantity":1,"Price":19970,"NumOrders":1},{"Side":"SELL","Quantity":1,"Price":27690,"NumOrders":1},{"Side":"SELL","Quantity":1,"Price":28927,"NumOrders":1},{"Side":"SELL","Quantity":1,"Price":31365,"NumOrders":1},{"Side":"SELL","Quantity":8587,"Price":40221,"NumOrders":1}]},"ImpliedBook":{"Buys":[{"Side":"BUY","Quantity":1,"Price":6114,"NumOrders":1},{"Side":"BUY","Quantity":1,"Price":5832,"NumOrders":1},{"Side":"BUY","Quantity":841,"Price":4689,"NumOrders":1},{"Side":"BUY","Quantity":1,"Price":2448,"NumOrders":1},{"Side":"BUY","Quantity":1,"Price":2447,"NumOrders":1}],"Sells":[{"Side":"SELL","Quantity":1,"Price":6114,"NumOrders":1},{"Side":"SELL","Quantity":1,"Price":6115,"NumOrders":1},{"Side":"SELL","Quantity":1,"Price":6116,"NumOrders":1},{"Side":"SELL","Quantity":1,"Price":6117,"NumOrders":1},{"Side":"SELL","Quantity":1,"Price":6118,"NumOrders":1}]}}]},{"SeqNum":2,"Channel":"SnapshotB","Messages":[{"SecurityID":2,"RepSeqNum":24,"LastMsgSeqNumProcessed":20,"MultiBook":{"Buys":[{"Side":"BUY","Quantity":1,"Price":11636,"NumOrders":1},{"Side":"BUY","Quantity":1,"Price":9353,"NumOrders":1},{"Side":"BUY","Quantity":591,"Price":987,"NumOrders":1},{"Side":"BUY","Quantity":1,"Price":537,"NumOrders":1},{"Side":"BUY","Quantity":1,"Price":536,"NumOrders":1}],"Sells":[{"Side":"SELL","Quantity":6907,"Price":17919,"NumOrders":1},{"Side":"SELL","Quantity":1,"Price":20917,"NumOrders":1},{"Side":"SELL","Quantity":1,"Price":21892,"NumOrders":1},{"Side":"SELL","Quantity":3610,"Price":23546,"NumOrders":1},{"Side":"SELL","Quantity":1,"Price":32003,"NumOrders":1}]},"ImpliedBook":{"Buys":[{"Side":"BUY","Quantity":1,"Price":9899,"NumOrders":1},{"Side":"BUY","Quantity":1,"Price":8102,"NumOrders":1},{"Side":"BUY","Quantity":1,"Price":8101,"NumOrders":1},{"Side":"BUY","Quantity":1,"Price":8100,"NumOrders":1},{"Side":"BUY","Quantity":1,"Price":8099,"NumOrders":1}],"Sells":[{"Side":"SELL","Quantity":1,"Price":15819,"NumOrders":1},{"Side":"SELL","Quantity":1,"Price":24765,"NumOrders":1},{"Side":"SELL","Quantity":1,"Price":29445,"NumOrders":1},{"Side":"SELL","Quantity":1,"Price":31334,"NumOrders":1},{"Side":"SELL","Quantity":1236,"Price":37239,"NumOrders":1}]}}]},{"SeqNum":3,"Channel":"SnapshotB","Messages":[{"SecurityID":1,"RepSeqNum":29,"LastMsgSeqNumProcessed":32,"MultiBook":{"Buys":[{"Side":"BUY","Quantity":1,"Price":19932,"NumOrders":1},{"Side":"BUY","Quantity":1,"Price":11052,"NumOrders":1},{"Side":"BUY","Quantity":1,"Price":9728,"NumOrders":1},{"Side":"BUY","Quantity":8946,"Price":2,"NumOrders":1},{"Side":"BUY","Quantity":5854,"Price":1,"NumOrders":1}],"Sells":[{"Side":"SELL","Quantity":1,"Price":19970,"NumOrders":1},{"Side":"SELL","Quantity":1,"Price":27690,"NumOrders":1},{"Side":"SELL","Quantity":1143,"Price":28927,"NumOrders":1},{"Side":"SELL","Quantity":1,"Price":31365,"NumOrders":1},{"Side":"SELL","Quantity":8587,"Price":40221,"NumOrders":1}]},"ImpliedBook":{"Buys":[{"Side":"BUY","Quantity":1,"Price":6114,"NumOrders":1},{"Side":"BUY","Quantity":1,"Price":5832,"NumOrders":1},{"Side":"BUY","Quantity":2438,"Price":4689,"NumOrders":1},{"Side":"BUY","Quantity":1,"Price":2448,"NumOrders":1},{"Side":"BUY","Quantity":1,"Price":2447,"NumOrders":1}],"Sells":[{},{},{"Side":"SELL","Quantity":1,"Price":6116,"NumOrders":1},{"Side":"SELL","Quantity":39,"Price":6117,"NumOrders":1},{"Side":"SELL","Quantity":1,"Price":6118,"NumOrders":1}]}}]},{"SeqNum":4,"Channel":"SnapshotB","Messages":[{"SecurityID":2,"RepSeqNum":37,"LastMsgSeqNumProcessed":32,"MultiBook":{"Buys":[{"Side":"BUY","Quantity":2283,"Price":11636,"NumOrders":1},{"Side":"BUY","Quantity":8366,"Price":9353,"NumOrders":1},{"Side":"BUY","Quantity":1797,"Price":987,"NumOrders":1},{"Side":"BUY","Quantity":5921,"Price":537,"NumOrders":1},{"Side":"BUY","Quantity":610,"Price":536,"NumOrders":1}],"Sells":[{"Side":"SELL","Quantity":6907,"Price":17919,"NumOrders":1},{"Side":"SELL","Quantity":282,"Price":20917,"NumOrders":1},{"Side":"SELL","Quantity":1,"Price":21892,"NumOrders":1},{"Side":"SELL","Quantity":8099,"Price":23546,"NumOrders":1},{}]},"ImpliedBook":{"Buys":[{"Side":"BUY","Quantity":1,"Price":9899,"NumOrders":1},{"Side":"BUY","Quantity":1,"Price":8102,"NumOrders":1},{"Side":"BUY","Quantity":1,"Price":8101,"NumOrders":1},{"Side":"BUY","Quantity":1,"Price":8100,"NumOrders":1},{"Side":"BUY","Quantity":1,"Price":8099,"NumOrders":1}],"Sells":[{"Side":"SELL","Quantity":1,"Price":15819,"NumOrders":1},{"Side":"SELL","Quantity":1,"Price":24765,"NumOrders":1},{"Side":"SELL","Quantity":8856,"Price":29445,"NumOrders":1},{"Side":"SELL","Quantity":1,"Price":31334,"NumOrders":1},{"Side":"SELL","Quantity":1236,"Price":37239,"NumOrders":1}]}}]}]}